kafeteria/__init__.py
kafeteria/core.py
kafeteria/scheduler.py
kafeteria/slack.py
kafeteria-0.4.0.dist-info/METADATA
kafeteria-0.4.0.dist-info/WHEEL
kafeteria-0.4.0.dist-info/licenses/LICENSE
kafeteria-0.4.0.dist-info/RECORD
