Metadata-Version: 2.4
Name: kafeteria
Version: 0.4.0
Summary: Asynchronously access the menu of the cafeterias at KAIST.
Author-email: Kimoon Han <khan@kaist.ac.kr>
License: MIT License
License-File: LICENSE
Keywords: aiohttp,asyncio,cafeteria,kaist
Classifier: Development Status :: 4 - Beta
Classifier: Framework :: AsyncIO
Classifier: Intended Audience :: Science/Research
Classifier: License :: OSI Approved :: MIT License
Classifier: Operating System :: OS Independent
Classifier: Programming Language :: Python :: 3.10
Classifier: Programming Language :: Python :: 3.11
Classifier: Programming Language :: Python :: 3.12
Classifier: Programming Language :: Python :: 3.13
Requires-Python: >=3.10
Requires-Dist: aiohttp>=3.11.11
Provides-Extra: slack
Requires-Dist: apscheduler>=3.11.0; extra == 'slack'
Requires-Dist: holidayskr>=0.2.0; extra == 'slack'
Requires-Dist: slack-sdk>=3.34.0; extra == 'slack'
